error_explorer/__init__.py
error_explorer/client.py
error_explorer/py.typed
error_explorer/scrubber.py
error_explorer/transport.py
error_explorer/types.py
error_explorer-1.2.0.dist-info/METADATA
error_explorer-1.2.0.dist-info/WHEEL
error_explorer-1.2.0.dist-info/top_level.txt
error_explorer-1.2.0.dist-info/RECORD
