Metadata-Version: 2.4
Name: error-explorer
Version: 1.2.0
Summary: Error Explorer SDK for Python - Automatic error tracking and monitoring
Author-email: Error Explorer <support@error-explorer.com>
License: MIT
Project-URL: Homepage, https://error-explorer.com
Project-URL: Documentation, https://docs.error-explorer.com/sdks/python
Project-URL: Repository, https://github.com/error-explorer/error-explorer-sdks
Project-URL: Issues, https://github.com/error-explorer/error-explorer-sdks/issues
Keywords: error-explorer,error-tracking,error-monitoring,exception-handling,debugging,logging,apm
Classifier: Development Status :: 5 - Production/Stable
Classifier: Intended Audience :: Developers
Classifier: License :: OSI Approved :: MIT License
Classifier: Operating System :: OS Independent
Classifier: Programming Language :: Python :: 3
Classifier: Programming Language :: Python :: 3.9
Classifier: Programming Language :: Python :: 3.10
Classifier: Programming Language :: Python :: 3.11
Classifier: Programming Language :: Python :: 3.12
Classifier: Topic :: Software Development :: Libraries :: Python Modules
Classifier: Topic :: System :: Logging
Classifier: Topic :: System :: Monitoring
Classifier: Typing :: Typed
Requires-Python: >=3.9
Requires-Dist: requests>=2.25.0
Requires-Dist: typing-extensions>=4.0.0; python_version < "3.11"
Provides-Extra: async
Requires-Dist: aiohttp>=3.8.0; extra == "async"
Provides-Extra: dev
Requires-Dist: pytest>=7.0.0; extra == "dev"
Requires-Dist: pytest-asyncio>=0.21.0; extra == "dev"
Requires-Dist: pytest-cov>=4.0.0; extra == "dev"
Requires-Dist: responses>=0.23.0; extra == "dev"
Requires-Dist: aioresponses>=0.7.4; extra == "dev"
Requires-Dist: mypy>=1.0.0; extra == "dev"
Requires-Dist: ruff>=0.1.0; extra == "dev"
